aiotailwind/__init__.py
aiotailwind/auth.py
aiotailwind/tailwind.py
aiotailwind-0.1.1.dist-info/LICENSE
aiotailwind-0.1.1.dist-info/METADATA
aiotailwind-0.1.1.dist-info/WHEEL
aiotailwind-0.1.1.dist-info/top_level.txt
aiotailwind-0.1.1.dist-info/RECORD
