Metadata-Version: 2.1
Name: aiotailwind
Version: 0.1.1
Summary: A small example package
Author: Paul Nicholls
Project-URL: Homepage, https://github.com/pauln/aiotailwind
Project-URL: Issues, https://github.com/pauln/aiotailwind/issues
Classifier: Programming Language :: Python :: 3
Classifier: License :: OSI Approved :: MIT License
Classifier: Operating System :: OS Independent
Classifier: Topic :: Home Automation
Classifier: Topic :: Software Development :: Libraries :: Python Modules
Requires-Python: >=3.8
License-File: LICENSE
